{"textures":{"0":"modelengine:entity/mso_cave_insect","1":"modelengine:entity/mso_cave_insect_e"},"elements":[{"name":"cube","from":[-0.8007364,1.9999998,5.7685785],"to":[1.5992637,10.4,8.168578],"rotation":{"angle":45.0,"axis":"y","origin":[1.5992637,1.9999998,7.5685787]},"faces":{"down":{"uv":[12.0,0.625,11.5,1.125],"rotation":0,"texture":"#0","tintindex":0},"east":{"uv":[4.5,8.875,4.0,10.625],"rotation":0,"texture":"#0","tintindex":0},"north":{"uv":[4.5,8.875,4.0,10.625],"rotation":0,"texture":"#0","tintindex":0},"south":{"uv":[4.5,8.875,4.0,10.625],"rotation":0,"texture":"#0","tintindex":0},"up":{"uv":[0.5,12.0,1.0,11.5],"rotation":0,"texture":"#0","tintindex":0},"west":{"uv":[4.5,8.875,4.0,10.625],"rotation":0,"texture":"#0","tintindex":0}}},{"name":"cube","from":[0.39926362,7.55,6.998579],"to":[8.349264,9.65,9.098579],"rotation":{"angle":45.0,"axis":"x","origin":[4.749264,8.6,7.7485785]},"faces":{"down":{"uv":[9.75,7.375,11.375,7.875],"rotation":0,"texture":"#0","tintindex":0},"east":{"uv":[12.0,1.625,11.5,2.125],"rotation":0,"texture":"#0","tintindex":0},"north":{"uv":[11.375,3.75,9.75,4.25],"rotation":0,"texture":"#0","tintindex":0},"south":{"uv":[11.375,4.25,9.75,4.75],"rotation":0,"texture":"#0","tintindex":0},"up":{"uv":[9.75,7.375,11.375,6.875],"rotation":0,"texture":"#0","tintindex":0},"west":{"uv":[2.0,11.5,1.5,12.0],"rotation":0,"texture":"#0","tintindex":0}}},{"name":"cube","from":[0.32426357,-1.0000005,6.3085785],"to":[0.32426357,1.9999998,9.668579],"rotation":{"angle":-22.5,"axis":"y","origin":[0.32426357,0.49999976,7.9885783]},"faces":{"down":{"uv":[0.0,0.0,0.0,0.75],"rotation":0,"texture":"#0","tintindex":0},"east":{"uv":[11.625,5.375,10.875,6.0],"rotation":0,"texture":"#0","tintindex":0},"north":{"uv":[0.0,0.0,0.0,0.625],"rotation":0,"texture":"#0","tintindex":0},"south":{"uv":[0.0,0.0,0.0,0.625],"rotation":0,"texture":"#0","tintindex":0},"up":{"uv":[0.0,0.75,0.0,0.0],"rotation":0,"texture":"#0","tintindex":0},"west":{"uv":[11.625,5.375,10.875,6.0],"rotation":0,"texture":"#0","tintindex":0}}},{"name":"cube","from":[0.32426357,-1.0000005,6.3085785],"to":[0.32426357,1.9999998,9.668579],"rotation":{"angle":-45.0,"axis":"y","origin":[0.32426357,0.49999976,7.9885783]},"faces":{"down":{"uv":[0.0,0.0,0.0,0.75],"rotation":0,"texture":"#0","tintindex":0},"east":{"uv":[11.625,5.375,10.875,6.0],"rotation":0,"texture":"#0","tintindex":0},"north":{"uv":[0.0,0.0,0.0,0.625],"rotation":0,"texture":"#0","tintindex":0},"south":{"uv":[0.0,0.0,0.0,0.625],"rotation":0,"texture":"#0","tintindex":0},"up":{"uv":[0.0,0.75,0.0,0.0],"rotation":0,"texture":"#0","tintindex":0},"west":{"uv":[11.625,5.375,10.875,6.0],"rotation":0,"texture":"#0","tintindex":0}}}],"display":{"head":{"translation":[0.0,-6.4,0.0],"rotation":[0.0,0.0,0.0],"scale":[3.8095,3.8095,3.8095]}}}